dbusmock
