Metadata-Version: 2.4
Name: python-dbusmock
Version: 0.38.1
Summary: Mock D-Bus objects
Author-email: Martin Pitt <martin@piware.de>
License:                    GNU LESSER GENERAL PUBLIC LICENSE
Project-URL: homepage, https://github.com/martinpitt/python-dbusmock
Classifier: License :: OSI Approved :: GNU Lesser General Public License v3 or later (LGPLv3+)
Classifier: Programming Language :: Python :: 3
Classifier: Development Status :: 6 - Mature
Classifier: Operating System :: POSIX :: Linux
Classifier: Operating System :: POSIX :: BSD
Classifier: Operating System :: Unix
Classifier: Topic :: Software Development :: Quality Assurance
Classifier: Topic :: Software Development :: Testing
Classifier: Topic :: Software Development :: Testing :: Mocking
Classifier: Topic :: Software Development :: Testing :: Unit
Classifier: Topic :: Software Development :: Libraries :: Python Modules
Requires-Python: >=3.8
License-File: COPYING
Requires-Dist: dbus-python
Dynamic: license-file
